README.md
setup.py
hbfm/__init__.py
hbfm/inline_coloring.py
hbfm/inline_list.py
hbfm/number_headers.py
hbfm/quote_uri_hash.py
hbfm/toc.py
hbfm.egg-info/PKG-INFO
hbfm.egg-info/SOURCES.txt
hbfm.egg-info/dependency_links.txt
hbfm.egg-info/top_level.txt