Metadata-Version: 1.1
Name: hbfm
Version: 1.0.0
Summary: HEARTBEATS Flavored Markdown extensions
Home-page: https://github.com/heartbeatsjp/markdown-extension-hbfm
Author: Toshiaki Baba
Author-email: toshiaki@netmark.jp
License: UNKNOWN
Platform: UNKNOWN
Classifier: Programming Language :: Python :: 2.7
Classifier: Programming Language :: Python :: 3.5
Classifier: Programming Language :: Python :: 3.6
